spacy_huggingface_pipelines/__init__.py
spacy_huggingface_pipelines/text_classification.py
spacy_huggingface_pipelines/token_classification.py
spacy_huggingface_pipelines/tests/__init__.py
spacy_huggingface_pipelines/tests/enable_gpu.py
spacy_huggingface_pipelines/tests/test_pipeline_components.py
spacy_huggingface_pipelines-0.0.4.dist-info/LICENSE
spacy_huggingface_pipelines-0.0.4.dist-info/METADATA
spacy_huggingface_pipelines-0.0.4.dist-info/WHEEL
spacy_huggingface_pipelines-0.0.4.dist-info/entry_points.txt
spacy_huggingface_pipelines-0.0.4.dist-info/top_level.txt
spacy_huggingface_pipelines-0.0.4.dist-info/RECORD
