Metadata-Version: 2.1
Name: spacy_huggingface_pipelines
Version: 0.0.4
Summary: spaCy wrapper for Hugging Face Transformers pipelines
Home-page: https://github.com/explosion/spacy-huggingface-pipelines
Author: Explosion
Author-email: contact@explosion.ai
License: MIT
Project-URL: Release notes, https://github.com/explosion/spacy-huggingface-pipelines/releases
Project-URL: Source, https://github.com/explosion/spacy-huggingface-pipelines
Classifier: Development Status :: 4 - Beta
Classifier: Environment :: Console
Classifier: Intended Audience :: Developers
Classifier: Intended Audience :: Science/Research
Classifier: Topic :: Scientific/Engineering
Classifier: Topic :: Scientific/Engineering :: Artificial Intelligence
Classifier: License :: OSI Approved :: MIT License
Classifier: Operating System :: POSIX :: Linux
Classifier: Operating System :: MacOS :: MacOS X
Classifier: Operating System :: Microsoft :: Windows
Classifier: Programming Language :: Python :: 3
Classifier: Programming Language :: Python :: 3.8
Classifier: Programming Language :: Python :: 3.9
Classifier: Programming Language :: Python :: 3.10
Classifier: Programming Language :: Python :: 3.11
Requires-Python: >=3.8
License-File: LICENSE
